Metadata-Version: 2.1
Name: lore
Version: 0.8.6
Summary: a framework for building and using data science
Home-page: http://github.com/instacart/lore
Author: Montana Low and Jeremy Stanley
Author-email: montana@instacart.com
License: MIT
Keywords: machine learning framework tensorflow airflow
Platform: UNKNOWN
Classifier: Development Status :: 4 - Beta
Classifier: License :: OSI Approved :: MIT License
Classifier: Programming Language :: Python :: 2
Classifier: Programming Language :: Python :: 2.7
Classifier: Programming Language :: Python :: 3
Classifier: Programming Language :: Python :: 3.5
Classifier: Programming Language :: Python :: 3.6
Classifier: Topic :: Scientific/Engineering
Classifier: Topic :: Scientific/Engineering :: Artificial Intelligence
Classifier: Environment :: Console
Requires-Python: >=3.0, !=3.0.*, !=3.1.*, !=3.2.*, !=3.3.*, !=3.4.*, <4
